{"title": "Salad onion potato cakes with poached eggs", "tags": null, "planning": {"prep_time": null, "cook_time": null, "total_time": "PT30M", "serves": "2"}, "ingredients": [{"item": "250g Maris Piper potatoes"}, {"item": "2 finely chopped salad onions"}, {"item": "1 tbsp roughly chopped parsley"}, {"item": "1 tbsp essential Waitrose Half Fat British Crème Fraîche"}, {"item": "½ tsp English mustard"}, {"item": "1 tbsp rapeseed oil"}, {"item": "2 medium eggs"}], "instructions": [], "nutrition": {"Energy": "1154.784kJ 276kcals", "Fat": "15.8g", "Saturated Fat": "3.7g", "Carbohydrate": "23.7g", "Sugars": "2.1g", "Salt": "0.9g"}, "image_url": "//d1v30bmd12dhid.cloudfront.net/static/version6/content/dam/waitrose/recipes/images/s/2011wked52-r04.jpg/_jcr_content/renditions/cq5dam.thumbnail.400.400.png"}